{"puzzle": "SPEAR BLAS CARP\nTRADE RUNT OBOE\nEIGHT ARTE CLAW\nASLEEP CHECKERS\nLEER INHERIT   \n   ESTEEM TASTE\nEBB TIED MAILED\nPROCEED LADLING\nOODLES MANE DDE\nSWEEP COSTLY   \n   REMORSE ALAS\nBUSINESS LAMENT\nERIC THEN IMAGE\nAGRA RELY NEVIN\nREEL ERSE TREES\n", "key": {"across": {"1": {"clue": "Opera prop", "word": "SPEAR"}, "6": {"clue": "\"Gil ___\"", "word": "BLAS"}, "10": {"clue": "Nag", "word": "CARP"}, "14": {"clue": "Swap", "word": "TRADE"}, "15": {"clue": "Sow's smallest offspring", "word": "RUNT"}, "16": {"clue": "Reed instrument", "word": "OBOE"}, "17": {"clue": "Figure for Dorothy Hamill", "word": "EIGHT"}, "18": {"clue": "Comedian Johnson", "word": "ARTE"}, "19": {"clue": "Talon", "word": "CLAW"}, "20": {"clue": "Word with fast and sound", "word": "ASLEEP"}, "22": {"clue": "Game involving 24 men", "word": "CHECKERS"}, "24": {"clue": "Nasty grin", "word": "LEER"}, "25": {"clue": "Come into", "word": "INHERIT"}, "27": {"clue": "Regard highly", "word": "ESTEEM"}, "29": {"clue": "This can't be disputed", "word": "TASTE"}, "33": {"clue": "Fred ___, \"Chicago\" lyricist", "word": "EBB"}, "36": {"clue": "Fit to be ___", "word": "TIED"}, "37": {"clue": "Posted", "word": "MAILED"}, "38": {"clue": "Make headway", "word": "PROCEED"}, "40": {"clue": "Chef's activity, at times", "word": "LADLING"}, "41": {"clue": "Gobs", "word": "OODLES"}, "42": {"clue": "Bison's pride", "word": "MANE"}, "43": {"clue": "H.S.T. successor", "word": "DDE"}, "44": {"clue": "Win every game in a series", "word": "SWEEP"}, "45": {"clue": "Dear", "word": "COSTLY"}, "47": {"clue": "Contrition", "word": "REMORSE"}, "49": {"clue": "\"O dear!\"", "word": "ALAS"}, "53": {"clue": "Word with show or monkey", "word": "BUSINESS"}, "56": {"clue": "Threnody", "word": "LAMENT"}, "58": {"clue": "Author Hoffer", "word": "ERIC"}, "59": {"clue": "Now's partner", "word": "THEN"}, "61": {"clue": "Idea", "word": "IMAGE"}, "62": {"clue": "Pearl Mosque site", "word": "AGRA"}, "63": {"clue": "Trust, with \"on\"", "word": "RELY"}, "64": {"clue": "Composer of \"Mighty Lak a Rose\"", "word": "NEVIN"}, "65": {"clue": "Strip of film", "word": "REEL"}, "66": {"clue": "Gaelic", "word": "ERSE"}, "67": {"clue": "Kilmer poem", "word": "TREES"}}, "down": {"1": {"clue": "Cry from Brock's fans", "word": "STEAL"}, "2": {"clue": "Lever", "word": "PRISE"}, "3": {"clue": "Symbol on U.S. coins", "word": "EAGLE"}, "4": {"clue": "Stick", "word": "ADHERE"}, "5": {"clue": "Network of nerves", "word": "RETE"}, "6": {"clue": "Bandeau", "word": "BRA"}, "7": {"clue": "Canted; careened", "word": "LURCHED"}, "8": {"clue": "Key work", "word": "ANTHEM"}, "9": {"clue": "Tip", "word": "STEER"}, "10": {"clue": "Stinger, e.g.", "word": "COCKTAIL"}, "11": {"clue": "Apt", "word": "ABLE"}, "12": {"clue": "Strain the voice", "word": "ROAR"}, "13": {"clue": "Church accommodations", "word": "PEWS"}, "21": {"clue": "Feels sympathy for", "word": "PITIES"}, "23": {"clue": "Bastion", "word": "CITADEL"}, "26": {"clue": "Requirement", "word": "NEED"}, "28": {"clue": "Make more precipitous", "word": "STEEPEN"}, "30": {"clue": "Coasted", "word": "SLID"}, "31": {"clue": "Be inclined", "word": "TEND"}, "32": {"clue": "Border", "word": "EDGE"}, "33": {"clue": "Poetry of a people", "word": "EPOS"}, "34": {"clue": "Forehead", "word": "BROW"}, "35": {"clue": "Portend", "word": "BODE"}, "37": {"clue": "Fireplace shelf", "word": "MANTEL"}, "39": {"clue": "Kind of collar or error", "word": "CLERICAL"}, "40": {"clue": "Colleen", "word": "LASS"}, "42": {"clue": "Snacks", "word": "MORSELS"}, "45": {"clue": "Pamper", "word": "COSHER"}, "46": {"clue": "Complain loudly", "word": "YAMMER"}, "48": {"clue": "A concern of Coleridge", "word": "METRE"}, "50": {"clue": "Sabbatical", "word": "LEAVE"}, "51": {"clue": "Actress Dickinson", "word": "ANGIE"}, "52": {"clue": "Tommy guns for Tommies", "word": "STENS"}, "53": {"clue": "Yellowstone Park denizen", "word": "BEAR"}, "54": {"clue": "Exhort", "word": "URGE"}, "55": {"clue": "Bold Bidder, to Spectacular Bid", "word": "SIRE"}, "57": {"clue": "\"___ Misbehavin'\"", "word": "AINT"}, "60": {"clue": "Comedian Louis", "word": "NYE"}}}, "metadata": {"author": "John R. Prosser", "editor": "Eugene T. Maleska", "rows": 15, "columns": 15, "date": {"month": 5, "day": 31, "year": 1979}}}