{"puzzle": "AGUSH AGER REP \nLORCA FREA AXIS\nMODIGLIANI SCAN\nANU GERM LOSENO\n   SLEEPYHOLLOW\nSPARES  PEPES  \nTIROS TARAS ISM\nALMS SHRED HOHO\nGEO SIRES BORON\n  RANGE  SENSES\nRIPVANWINKLE   \nALLEGE NOIL AOH\nFLAN DILETTANTE\nTUTU UVAL HITON\n SEE PAWS ESSES\n", "key": {"across": {"1": {"clue": "Bubbling up.", "word": "AGUSH"}, "6": {"clue": "Field Lat.", "word": "AGER"}, "10": {"clue": "House member Abbr.", "word": "REP"}, "13": {"clue": "Spanish playwright.", "word": "LORCA"}, "14": {"clue": "Teutonic goddess.", "word": "FREA"}, "15": {"clue": "W. W. II group.", "word": "AXIS"}, "17": {"clue": "Painter of ectomorphic women.", "word": "MODIGLIANI"}, "19": {"clue": "Analyze verse.", "word": "SCAN"}, "20": {"clue": "Babylonian sky god.", "word": "ANU"}, "21": {"clue": "Origin.", "word": "GERM"}, "22": {"clue": "___ sleep over.", "word": "LOSENO"}, "24": {"clue": "Locale of legend.", "word": "SLEEPYHOLLOW"}, "26": {"clue": "Some tires.", "word": "SPARES"}, "29": {"clue": "Many Mexicanos.", "word": "PEPES"}, "30": {"clue": "Weather satellite.", "word": "TIROS"}, "31": {"clue": "Bulba.", "word": "TARAS"}, "33": {"clue": "Doctrine.", "word": "ISM"}, "36": {"clue": "Gifts of a kind.", "word": "ALMS"}, "37": {"clue": "Scrap.", "word": "SHRED"}, "38": {"clue": "Exclamation of surprise.", "word": "HOHO"}, "39": {"clue": "Washington, for one Abbr.", "word": "GEO"}, "40": {"clue": "Begets.", "word": "SIRES"}, "41": {"clue": "Element.", "word": "BORON"}, "42": {"clue": "Scope.", "word": "RANGE"}, "44": {"clue": "Taste and touch.", "word": "SENSES"}, "45": {"clue": "Late sleeper.", "word": "RIPVANWINKLE"}, "49": {"clue": "Declare positively.", "word": "ALLEGE"}, "50": {"clue": "Short wool fiber.", "word": "NOIL"}, "51": {"clue": "Hibernian group.", "word": "AOH"}, "54": {"clue": "Filled cake Fr.", "word": "FLAN"}, "55": {"clue": "Art lover for amusement.", "word": "DILETTANTE"}, "58": {"clue": "Ballet skirt.", "word": "TUTU"}, "59": {"clue": "Grapelike.", "word": "UVAL"}, "60": {"clue": "Discover, as a solution Colloq.", "word": "HITON"}, "61": {"clue": "Visit.", "word": "SEE"}, "62": {"clue": "Hands Colloq.", "word": "PAWS"}, "63": {"clue": "Letters.", "word": "ESSES"}}, "down": {"1": {"clue": "Gluck.", "word": "ALMA"}, "2": {"clue": "Make an entrance.", "word": "GOON"}, "3": {"clue": "Hindustani.", "word": "URDU"}, "4": {"clue": "School subject Abbr.", "word": "SCI"}, "5": {"clue": "Negotiates tediously.", "word": "HAGGLES"}, "6": {"clue": "Full of ardor.", "word": "AFIRE"}, "7": {"clue": "Member of the family Colloq.", "word": "GRAMP"}, "8": {"clue": "Poetic contraction.", "word": "EEN"}, "9": {"clue": "Terminal.", "word": "RAILHEAD"}, "10": {"clue": "Come to grips with Colloq.", "word": "RASSLE"}, "11": {"clue": "Longfellow's poetic injunctions.", "word": "EXCELSIORS"}, "12": {"clue": "Grand ___.", "word": "PIANO"}, "16": {"clue": "TV trouble.", "word": "SNOW"}, "18": {"clue": "Famous FFV.", "word": "LEES"}, "23": {"clue": "'Scuse, please!", "word": "OOPS"}, "24": {"clue": "Welcome signs to \"angels.\"", "word": "SROS"}, "25": {"clue": "Historic town of Belgium.", "word": "YPRES"}, "26": {"clue": "Unaccompanied Colloq.", "word": "STAG"}, "27": {"clue": "Nap.", "word": "PILE"}, "28": {"clue": "Specially hardened steel.", "word": "ARMORPLATE"}, "31": {"clue": "Lost deliberately Colloq.", "word": "THREW"}, "32": {"clue": "Common verb.", "word": "ARE"}, "34": {"clue": "Blucher.", "word": "SHOE"}, "35": {"clue": "See 25 Down.", "word": "MONS"}, "37": {"clue": "Volunteered.", "word": "SIGNEDUP"}, "38": {"clue": "Sharpen.", "word": "HONE"}, "40": {"clue": "Catch.", "word": "SNAG"}, "41": {"clue": "___ cat.", "word": "BELLTHE"}, "43": {"clue": "Means of access.", "word": "AVENUE"}, "44": {"clue": "Revue offering.", "word": "SKIT"}, "45": {"clue": "Large number Colloq.", "word": "RAFT"}, "46": {"clue": "Drawing in a book Abbr.", "word": "ILLUS"}, "47": {"clue": "Relative of a sort.", "word": "INLAW"}, "48": {"clue": "French f\u00e8tes.", "word": "NOELS"}, "51": {"clue": "Leaf cutters.", "word": "ANTS"}, "52": {"clue": "Oklahoma Indian.", "word": "OTOE"}, "53": {"clue": "Some birds.", "word": "HENS"}, "56": {"clue": "Ragweed genus.", "word": "IVA"}, "57": {"clue": "South American mammals.", "word": "AIS"}}}, "metadata": {"author": "Unknown", "editor": "Margaret Farrar", "rows": 15, "columns": 15, "date": {"month": 11, "day": 17, "year": 1965}}}