{"puzzle": "POSEN  STA SHEB\nARENA AWAD MODE\nWINDSHIELDWIPER\nABSOLUTECEILING\nTIER ESP DDE   \n   SPY STTERESA\nADIEU VERA  RIP\nFORENSICEXPERTS\nALI  OTOE ENSUE\nRESTEDON SEA   \n   ULA DYE MEGA\nPENCILSHARPENER\nCLASSICALBALLET\nBESO MANE CEASE\nSCAN ETD  TRIES\n", "key": {"across": {"1": {"clue": "City north of Breslau", "word": "POSEN"}, "6": {"clue": "Penn, for one Abbr.", "word": "STA"}, "9": {"clue": "Actor/singer Wooley", "word": "SHEB"}, "13": {"clue": "Place for a match", "word": "ARENA"}, "14": {"clue": "Make ___ (get paid well)", "word": "AWAD"}, "15": {"clue": "Means", "word": "MODE"}, "16": {"clue": "Rain check?", "word": "WINDSHIELDWIPER"}, "19": {"clue": "Aircraft's altitude limit", "word": "ABSOLUTECEILING"}, "20": {"clue": "Bank", "word": "TIER"}, "21": {"clue": "Special insight", "word": "ESP"}, "22": {"clue": "\"Crusade in Europe\" auth.", "word": "DDE"}, "23": {"clue": "Bug someone, e.g.", "word": "SPY"}, "25": {"clue": "\"The Way of Perfection\" writer", "word": "STTERESA"}, "30": {"clue": "Word on the way out?", "word": "ADIEU"}, "33": {"clue": "Designer Wang", "word": "VERA"}, "34": {"clue": "Slugger's swing", "word": "RIP"}, "35": {"clue": "Crime lab staff", "word": "FORENSICEXPERTS"}, "39": {"clue": "Former ring leader", "word": "ALI"}, "40": {"clue": "Language from which \"Nebraska\" comes", "word": "OTOE"}, "41": {"clue": "Come after", "word": "ENSUE"}, "42": {"clue": "Lay atop", "word": "RESTEDON"}, "45": {"clue": "It has a wet floor", "word": "SEA"}, "46": {"clue": "Suffix with form", "word": "ULA"}, "47": {"clue": "Turn black, maybe", "word": "DYE"}, "49": {"clue": "Prefix with star or bucks", "word": "MEGA"}, "53": {"clue": "Point producer", "word": "PENCILSHARPENER"}, "58": {"clue": "\u00c9toile's area", "word": "CLASSICALBALLET"}, "59": {"clue": "Don Juan's kiss", "word": "BESO"}, "60": {"clue": "Zebra feature", "word": "MANE"}, "61": {"clue": "Break off", "word": "CEASE"}, "62": {"clue": "Some camera work", "word": "SCAN"}, "63": {"clue": "Flight board listing Abbr.", "word": "ETD"}, "64": {"clue": "Strains", "word": "TRIES"}}, "down": {"1": {"clue": "Manhandle", "word": "PAWAT"}, "2": {"clue": "Antelope with spikelike horns", "word": "ORIBI"}, "3": {"clue": "Meaning", "word": "SENSE"}, "4": {"clue": "Check beneficiary", "word": "ENDORSEE"}, "5": {"clue": "Pel\u00e9's org.", "word": "NASL"}, "6": {"clue": "It's in the same position every minute", "word": "SWEEPSECONDHAND"}, "7": {"clue": "Magnesium silicate", "word": "TALC"}, "8": {"clue": "A grand total may include it", "word": "ADDEDTAX"}, "9": {"clue": "Luck or fate, at times", "word": "SMILER"}, "10": {"clue": "They have their reservations", "word": "HOPI"}, "11": {"clue": "Fall venue", "word": "EDEN"}, "12": {"clue": "\"Lulu\" composer", "word": "BERG"}, "14": {"clue": "Islets", "word": "AITS"}, "17": {"clue": "Army helicopter", "word": "HUEY"}, "18": {"clue": "Like some loads", "word": "WIDE"}, "24": {"clue": "\"Let us spray,\" e.g.", "word": "PUN"}, "26": {"clue": "One may undergo surgery", "word": "TREE"}, "27": {"clue": "Slips", "word": "ERRS"}, "28": {"clue": "Ex ___ (not in its original habitat)", "word": "SITU"}, "29": {"clue": "Stained-glass window site", "word": "APSE"}, "30": {"clue": "Way off", "word": "AFAR"}, "31": {"clue": "Charity distribution", "word": "DOLE"}, "32": {"clue": "Freesia's relative", "word": "IRIS"}, "33": {"clue": "Marlon's Oscar-winning role", "word": "VITO"}, "36": {"clue": "Carbon dioxide absorber", "word": "SODALIME"}, "37": {"clue": "Second of April?", "word": "PEE"}, "38": {"clue": "Pottery worker, sometimes", "word": "ENAMELER"}, "43": {"clue": "Copper Bowl locale", "word": "TUCSON"}, "44": {"clue": "48-Down team", "word": "ELIS"}, "45": {"clue": "Vojvodina resident", "word": "SERB"}, "48": {"clue": "See 44-Down", "word": "YALE"}, "50": {"clue": "Zhou ___", "word": "ENLAI"}, "51": {"clue": "Fools", "word": "GEESE"}, "52": {"clue": "C\u00e1diz crafts", "word": "ARTES"}, "53": {"clue": "Highly toxic pollutants", "word": "PCBS"}, "54": {"clue": "Juice Abbr.", "word": "ELEC"}, "55": {"clue": "Magellan's org.", "word": "NASA"}, "56": {"clue": "\"Begone!\"", "word": "SCAT"}, "57": {"clue": "A handshake may seal it", "word": "PACT"}}}, "metadata": {"author": "Jim Page", "editor": "Will Shortz", "rows": 15, "columns": 15, "date": {"month": 6, "day": 2, "year": 2001}}}