{"puzzle": "MESS STAPLE CPU\nEXPO TERROR HAG\nTHEBOUNCINGBALL\nROE ANTON  ARMY\nORDERS  CAPRA  \nSTYX  THELEADER\n   OSSIA TAKETO\nOVA THATCAR SEZ\nJAGUAR EARLY   \nONESHEART  SORT\n  GELDS  FOLLOW\nZERO  KARAT DEI\nINONESFOOTSTEPS\nNYU ROOKIE ASET\nGAP APRILS ITRY\n", "key": {"across": {"1": {"clue": "Job for a cleanup crew", "word": "MESS"}, "5": {"clue": "Fasten, in a way", "word": "STAPLE"}, "11": {"clue": "PC \"brain\"", "word": "CPU"}, "14": {"clue": "Place for a pavilion", "word": "EXPO"}, "15": {"clue": "Wild child", "word": "TERROR"}, "16": {"clue": "Cauldron stirrer", "word": "HAG"}, "17": {"clue": "Sing-along direction", "word": "THEBOUNCINGBALL"}, "20": {"clue": "Masago, e.g., at a sushi bar", "word": "ROE"}, "21": {"clue": "Writer Chekhov", "word": "ANTON"}, "22": {"clue": "Team nicknamed the Black Knights", "word": "ARMY"}, "23": {"clue": "Obey", "word": "ORDERS"}, "25": {"clue": "Frank with six Oscars", "word": "CAPRA"}, "28": {"clue": "River ferried by Charon", "word": "STYX"}, "29": {"clue": "Children's game", "word": "THELEADER"}, "33": {"clue": "Direction to an alternative musical passage", "word": "OSSIA"}, "36": {"clue": "Become fond of", "word": "TAKETO"}, "37": {"clue": "Fertility lab stock", "word": "OVA"}, "40": {"clue": "Chase scene shout", "word": "THATCAR"}, "42": {"clue": "\"___ who?\"", "word": "SEZ"}, "43": {"clue": "Figure of many a Mayan deity", "word": "JAGUAR"}, "45": {"clue": "Before dawn, say", "word": "EARLY"}, "47": {"clue": "Pursue a passion", "word": "ONESHEART"}, "49": {"clue": "Spreadsheet function", "word": "SORT"}, "53": {"clue": "Neuters", "word": "GELDS"}, "54": {"clue": "Word missing from the answers to 17-, 23-, 29-, 40-, 47- and 62-Across", "word": "FOLLOW"}, "56": {"clue": "Worthless sort", "word": "ZERO"}, "58": {"clue": "One of 22 in a Krugerrand", "word": "KARAT"}, "61": {"clue": "\"Agnus ___\"", "word": "DEI"}, "62": {"clue": "Do as a mentor did, say", "word": "INONESFOOTSTEPS"}, "66": {"clue": "Home of the Tisch Sch. of the Arts", "word": "NYU"}, "67": {"clue": "First-timer", "word": "ROOKIE"}, "68": {"clue": "Play ___ (enjoy some tennis)", "word": "ASET"}, "69": {"clue": "Longtime mall chain", "word": "GAP"}, "70": {"clue": "Times for showers", "word": "APRILS"}, "71": {"clue": "Modest response to kudos", "word": "ITRY"}}, "down": {"1": {"clue": "Some urban transit systems", "word": "METROS"}, "2": {"clue": "Urge on", "word": "EXHORT"}, "3": {"clue": "Quick", "word": "SPEEDY"}, "4": {"clue": "Turn on the waterworks", "word": "SOB"}, "5": {"clue": "Knocks for a loop", "word": "STUNS"}, "6": {"clue": "Oxygen ___", "word": "TENT"}, "7": {"clue": "Sacramento's former ___ Arena", "word": "ARCO"}, "8": {"clue": "Singer whose \"name\" was once a symbol", "word": "PRINCE"}, "9": {"clue": "Chaney of film", "word": "LON"}, "10": {"clue": "Dyne-centimeter", "word": "ERG"}, "11": {"clue": "Game with many \"points\"", "word": "CHARADES"}, "12": {"clue": "Lifeline's location", "word": "PALM"}, "13": {"clue": "Like a 16-Across", "word": "UGLY"}, "18": {"clue": "Thole insert", "word": "OAR"}, "19": {"clue": "Netanyahu's successor, 1999", "word": "BARAK"}, "24": {"clue": "Prefix with biology", "word": "EXO"}, "26": {"clue": "The constellation Ara", "word": "ALTAR"}, "27": {"clue": "Cultured gem", "word": "PEARL"}, "29": {"clue": "___ Maria (liqueur)", "word": "TIA"}, "30": {"clue": "Misanthrope, e.g.", "word": "HATER"}, "31": {"clue": "Balmy time in Bordeaux", "word": "ETE"}, "32": {"clue": "\"Frasier\" role", "word": "ROZ"}, "34": {"clue": "Lesley of \"60 Minutes\"", "word": "STAHL"}, "35": {"clue": "Tiny bit", "word": "SHRED"}, "37": {"clue": "Acapulco \"eye\"", "word": "OJO"}, "38": {"clue": "Transportation for many a rock band", "word": "VAN"}, "39": {"clue": "Demographic division", "word": "AGEGROUP"}, "41": {"clue": "Whiskas eater", "word": "CAT"}, "44": {"clue": "Apply to", "word": "USEON"}, "46": {"clue": "Fashion monogram", "word": "YSL"}, "48": {"clue": "Invite, as trouble", "word": "ASKFOR"}, "50": {"clue": "Guinness superlative", "word": "OLDEST"}, "51": {"clue": "Richard with a much-used thumb", "word": "ROEPER"}, "52": {"clue": "Like pretzels, typically", "word": "TWISTY"}, "54": {"clue": "Clotho and sisters", "word": "FATES"}, "55": {"clue": "Game extenders Abbr.", "word": "OTS"}, "56": {"clue": "Throw a barb at", "word": "ZING"}, "57": {"clue": "\"And Winter Came ...\" singer", "word": "ENYA"}, "59": {"clue": "Isao of the Golf Hall of Fame", "word": "AOKI"}, "60": {"clue": "Stir up", "word": "ROIL"}, "63": {"clue": "Sports stat that's best when low", "word": "ERA"}, "64": {"clue": "Bribe", "word": "SOP"}, "65": {"clue": "___ chi", "word": "TAI"}}}, "metadata": {"author": "Jim Hilger", "editor": "Will Shortz", "rows": 15, "columns": 15, "date": {"month": 9, "day": 7, "year": 2011}}}