{"puzzle": " ABAFT NASALIS HAMNET  \nORACLE ESTREAT EPAULET \nRICHARDBURBAGE LOGISTIC\nGLOT NEUN ORONTES TIREE\nALN   ELDERS TENTS EARS\nNAIF GRAEAE   SAALE DST\nITALIA ERST SAT TATA   \nCENACLE  TUBAL SEMESTER\n   ROASTS MOMENTS STALE\nARDEN TRUE AUGER TIARAS\nNEED DRUMMERS RICHARDII\nASE TEAS UNSER NOUN ING\nHIPPOLYTA THRONGED OVEN\nIDEATE ENARE BEER BLESS\nTENET REDLEAD ARCARO   \nASSAILED LADED  ETONIAN\n   NEAP EST FOPS ISOLDE\nALB SMELL   EROTIC SLAW\nSEEP PLIES DRYROT   ACT\nPADUA LAMINAR TOBE ORLO\nSPALPEEN SEVENAGESOFMAN\n SUSANNA AVERAGE TUNERS\n  BERETS LESSEES ERODE \n", "key": {"across": {"1": {"clue": "Astern Naut.", "word": "ABAFT"}, "6": {"clue": "Muscle of the nose.", "word": "NASALIS"}, "13": {"clue": "Shakespeare's son, twin of Judith.", "word": "HAMNET"}, "19": {"clue": "\"I am Sir ___ ... \"", "word": "ORACLE"}, "20": {"clue": "Legal copy.", "word": "ESTREAT"}, "21": {"clue": "Shoulder ornament.", "word": "EPAULET"}, "23": {"clue": "Actor friend of Shakespeare.", "word": "RICHARDBURBAGE"}, "25": {"clue": "Of an army's transport and supply services.", "word": "LOGISTIC"}, "27": {"clue": "Mastery of languages Comb. form.", "word": "GLOT"}, "28": {"clue": "Nine Ger.", "word": "NEUN"}, "29": {"clue": "Syrian river.", "word": "ORONTES"}, "31": {"clue": "One of the Inner Hebrides.", "word": "TIREE"}, "32": {"clue": "Northumberland river.", "word": "ALN"}, "33": {"clue": "Trees.", "word": "ELDERS"}, "35": {"clue": "Scenery for \"Troilus and Cressida.\"", "word": "TENTS"}, "37": {"clue": "\"Lend me your ___.\"", "word": "EARS"}, "38": {"clue": "Artless.", "word": "NAIF"}, "40": {"clue": "Guardians of the Gorgons Gr. Myth.", "word": "GRAEAE"}, "41": {"clue": "German river into the Elbe.", "word": "SAALE"}, "43": {"clue": "Timetable abbreviation.", "word": "DST"}, "44": {"clue": "Where Livorno is.", "word": "ITALIA"}, "46": {"clue": "Of old Poet.", "word": "ERST"}, "47": {"clue": "\"She ___ like patience on a monument.\"", "word": "SAT"}, "49": {"clue": "Bye-bye.", "word": "TATA"}, "51": {"clue": "Room of the Last Supper.", "word": "CENACLE"}, "53": {"clue": "Shylock's friend.", "word": "TUBAL"}, "55": {"clue": "School year division.", "word": "SEMESTER"}, "59": {"clue": "Dishes.", "word": "ROASTS"}, "62": {"clue": "Twinklings.", "word": "MOMENTS"}, "64": {"clue": "\" ... nor custom ___ her infinite variety.\"", "word": "STALE"}, "65": {"clue": "Orlando's trysting place.", "word": "ARDEN"}, "68": {"clue": "Certain.", "word": "TRUE"}, "70": {"clue": "Tool.", "word": "AUGER"}, "71": {"clue": "Papal crowns.", "word": "TIARAS"}, "72": {"clue": "Requirement.", "word": "NEED"}, "73": {"clue": "Band members.", "word": "DRUMMERS"}, "75": {"clue": "King murdered by Exton.", "word": "RICHARDII"}, "77": {"clue": "Ibsen role.", "word": "ASE"}, "78": {"clue": "Certain parties.", "word": "TEAS"}, "79": {"clue": "Ours Ger.", "word": "UNSER"}, "81": {"clue": "Substantive.", "word": "NOUN"}, "82": {"clue": "Common suffix.", "word": "ING"}, "83": {"clue": "Queen of the Amazons.", "word": "HIPPOLYTA"}, "86": {"clue": "Moved in multitudes.", "word": "THRONGED"}, "88": {"clue": "Stove part.", "word": "OVEN"}, "89": {"clue": "Imagine.", "word": "IDEATE"}, "90": {"clue": "Finnish lake.", "word": "ENARE"}, "92": {"clue": "Drink.", "word": "BEER"}, "93": {"clue": "Consecrate.", "word": "BLESS"}, "94": {"clue": "Dogma.", "word": "TENET"}, "95": {"clue": "Substance used in glassmaking.", "word": "REDLEAD"}, "97": {"clue": "Jockey of Derby fame.", "word": "ARCARO"}, "99": {"clue": "Attacked.", "word": "ASSAILED"}, "101": {"clue": "Bailed.", "word": "LADED"}, "103": {"clue": "English student.", "word": "ETONIAN"}, "107": {"clue": "Kind of tide.", "word": "NEAP"}, "108": {"clue": "Common suffix.", "word": "EST"}, "109": {"clue": "Coxcombs.", "word": "FOPS"}, "112": {"clue": "Singer of the \"Liebestod.\"", "word": "ISOLDE"}, "113": {"clue": "Church robe.", "word": "ALB"}, "116": {"clue": "Aroma.", "word": "SMELL"}, "118": {"clue": "Amatory.", "word": "EROTIC"}, "120": {"clue": "Cabbage salad.", "word": "SLAW"}, "121": {"clue": "Ooze.", "word": "SEEP"}, "123": {"clue": "Folds.", "word": "PLIES"}, "125": {"clue": "Deterioration.", "word": "DRYROT"}, "126": {"clue": "Law.", "word": "ACT"}, "127": {"clue": "Baptista's home.", "word": "PADUA"}, "129": {"clue": "Having scales.", "word": "LAMINAR"}, "131": {"clue": "Hamlet's alternative.", "word": "TOBE"}, "133": {"clue": "Flat plinth.", "word": "ORLO"}, "134": {"clue": "Irish rogue.", "word": "SPALPEEN"}, "136": {"clue": "Subject of Jacques' immortal speech.", "word": "SEVENAGESOFMAN"}, "139": {"clue": "Shakespeare's eldest child.", "word": "SUSANNA"}, "140": {"clue": "Soso.", "word": "AVERAGE"}, "141": {"clue": "Piano ___.", "word": "TUNERS"}, "142": {"clue": "Basque caps.", "word": "BERETS"}, "143": {"clue": "Certain tenants.", "word": "LESSEES"}, "144": {"clue": "Wear away.", "word": "ERODE"}}, "down": {"1": {"clue": "Having covered seeds Bot.", "word": "ARILLATE"}, "2": {"clue": "Follower of a certain theory.", "word": "BACONIAN"}, "3": {"clue": "Eight Ger.", "word": "ACHT"}, "4": {"clue": "State Abbr.", "word": "FLA"}, "5": {"clue": "Coastal bird.", "word": "TERN"}, "6": {"clue": "Components of galaxies.", "word": "NEBULAE"}, "7": {"clue": "Into parts.", "word": "ASUNDER"}, "8": {"clue": "Ship Abbr.", "word": "STR"}, "9": {"clue": "Type of botanical garden.", "word": "ARBORETUM"}, "10": {"clue": "Salvini and Booth were famous ones.", "word": "LEARS"}, "11": {"clue": "Othello's ensign.", "word": "IAGO"}, "12": {"clue": "Levy a tax.", "word": "STENT"}, "13": {"clue": "Heroine of 91 Down.", "word": "HELENA"}, "14": {"clue": "Renegades.", "word": "APOSTATES"}, "15": {"clue": "Periodical Abbr.", "word": "MAG"}, "16": {"clue": "Night Fr.", "word": "NUIT"}, "17": {"clue": "Oliver Wendell Holmes heroine.", "word": "ELSIE"}, "18": {"clue": "Group of four.", "word": "TETRAD"}, "19": {"clue": "Constitutional.", "word": "ORGANIC"}, "22": {"clue": "Rows.", "word": "TIERS"}, "24": {"clue": "Sambar.", "word": "DEER"}, "26": {"clue": "___ la vie.", "word": "CEST"}, "30": {"clue": "Assay.", "word": "TEST"}, "34": {"clue": "\"It is the ___ and Juliet is the sun!\"", "word": "EAST"}, "36": {"clue": "Old card game.", "word": "SLAM"}, "39": {"clue": "Became enraged (with \"up\").", "word": "FLARED"}, "40": {"clue": "Festive.", "word": "GALA"}, "42": {"clue": "Annual, as winds.", "word": "ETESIAN"}, "45": {"clue": "Church image.", "word": "ICON"}, "47": {"clue": "To enjoy oneself Fr.", "word": "SAMUSER"}, "48": {"clue": "Shake ___ (hurry).", "word": "ALEG"}, "50": {"clue": "\"There was ___ danced ... \"", "word": "ASTAR"}, "52": {"clue": "Candidate for the pound.", "word": "ESTRAY"}, "54": {"clue": "Tavern frequented by Falstaff.", "word": "BOARSHEAD"}, "55": {"clue": "Carpenter's timber.", "word": "STRINGER"}, "56": {"clue": "Tending to delay.", "word": "TARDIVE"}, "57": {"clue": "Ladies of Camelot days.", "word": "ELAINES"}, "58": {"clue": "Yields.", "word": "RESIGNS"}, "60": {"clue": "Put under guardianship.", "word": "TRUSTEED"}, "61": {"clue": "\"What ___ owes he the Jew?\"", "word": "SUM"}, "63": {"clue": "Father of Abner.", "word": "NER"}, "65": {"clue": "Persian goddess of fruitfulness.", "word": "ANAHITA"}, "66": {"clue": "Has domicile.", "word": "RESIDES"}, "67": {"clue": "Becomes more profound.", "word": "DEEPENS"}, "69": {"clue": "Ratite bird.", "word": "EMU"}, "71": {"clue": "Dull sound.", "word": "THUD"}, "73": {"clue": "Printer's delta.", "word": "DELE"}, "74": {"clue": "Ask earnestly.", "word": "ENTREAT"}, "76": {"clue": "Compel.", "word": "COERCE"}, "78": {"clue": "Befuddled ones Dial.", "word": "TOTTIES"}, "80": {"clue": "Deprive of.", "word": "ROB"}, "84": {"clue": "Song of triumph.", "word": "PAEAN"}, "85": {"clue": "Moreover.", "word": "AND"}, "87": {"clue": "Teachers' group Abbr.", "word": "NEA"}, "88": {"clue": "Early name of mount where Hercules captured the boar.", "word": "OLONOS"}, "91": {"clue": "\"___ Well ... \"", "word": "ALLS"}, "93": {"clue": "Kinsmen Abbr.", "word": "BROS"}, "95": {"clue": "Causing aversion.", "word": "REPELLENT"}, "96": {"clue": "Procrastinators.", "word": "DEFERRERS"}, "98": {"clue": "Of Suffix.", "word": "ATIC"}, "100": {"clue": "Torch Poet.", "word": "LAMP"}, "102": {"clue": "Boat.", "word": "DORY"}, "104": {"clue": "Poorly equipped.", "word": "ILLARMED"}, "105": {"clue": "Character in \"Bleak House.\"", "word": "ADACLARE"}, "106": {"clue": "Sir Isaac and others.", "word": "NEWTONS"}, "108": {"clue": "Type of school Abbr.", "word": "ELEM"}, "110": {"clue": "Cost of carrying.", "word": "PORTAGE"}, "111": {"clue": "Comedians' foils.", "word": "STOOGES"}, "113": {"clue": "Clown's gift to Cleopatra.", "word": "ASPS"}, "114": {"clue": "Bounds.", "word": "LEAPS"}, "115": {"clue": "Smear.", "word": "BEDAUB"}, "117": {"clue": "Climbing plants.", "word": "LIANAS"}, "119": {"clue": "\"If ___ now, 'tis not to come ... \"", "word": "ITBE"}, "122": {"clue": "Beat.", "word": "PULSE"}, "124": {"clue": "Strong fiber.", "word": "SISAL"}, "125": {"clue": "Garroway and Sime.", "word": "DAVES"}, "128": {"clue": "Relative of the peba.", "word": "APAR"}, "130": {"clue": "Granular snow.", "word": "NEVE"}, "132": {"clue": "East Span.", "word": "ESTE"}, "133": {"clue": "\"It's ___ consequence.\"", "word": "OFNO"}, "135": {"clue": "Chemical suffix.", "word": "ENE"}, "137": {"clue": "No Scot.", "word": "NAE"}, "138": {"clue": "Pronoun.", "word": "OUR"}}}, "metadata": {"author": "W. E. Jones", "editor": "Margaret Farrar", "rows": 23, "columns": 23, "date": {"month": 8, "day": 18, "year": 1957}}}