{"puzzle": "ORAN SNACK PRIM\nCORA TULLE LENO\nADAM URGES AGAL\n SPEAKSOFTLYAND\n    MAE  RIPLEY\nFLAMES CREDO   \nLIMAN BAAL SIMA\nALUI SORTS SAAR\nWARN PLEA CUMIN\n   STILT BUMBLE\nSTATOR  OUR    \nCARRYABIGSTICK \nAKEE LIMIT PHEW\nLENA ELEVE IONA\nENAM DETER LOOT\n", "key": {"across": {"1": {"clue": "Algerian city", "word": "ORAN"}, "5": {"clue": "Dieter's sacrifice", "word": "SNACK"}, "10": {"clue": "Proper", "word": "PRIM"}, "14": {"clue": "Uncas's love", "word": "CORA"}, "15": {"clue": "Fine net", "word": "TULLE"}, "16": {"clue": "Mesh fabric", "word": "LENO"}, "17": {"clue": "Furniture style", "word": "ADAM"}, "18": {"clue": "Impels", "word": "URGES"}, "19": {"clue": "Arab headband", "word": "AGAL"}, "20": {"clue": "Part of T.R.'s advice", "word": "SPEAKSOFTLYAND"}, "23": {"clue": "West", "word": "MAE"}, "24": {"clue": "\"Believe It or Not\" man", "word": "RIPLEY"}, "25": {"clue": "Moth attractors", "word": "FLAMES"}, "29": {"clue": "Belief", "word": "CREDO"}, "31": {"clue": "Lagoon", "word": "LIMAN"}, "32": {"clue": "Semitic deity", "word": "BAAL"}, "33": {"clue": "Igneous rock", "word": "SIMA"}, "37": {"clue": "His Fr.", "word": "ALUI"}, "38": {"clue": "Out of ___ (peevish)", "word": "SORTS"}, "39": {"clue": "German valley", "word": "SAAR"}, "40": {"clue": "Caution", "word": "WARN"}, "41": {"clue": "Appeal", "word": "PLEA"}, "42": {"clue": "Aromatic seed", "word": "CUMIN"}, "43": {"clue": "Marsh bird", "word": "STILT"}, "45": {"clue": "Be all thumbs", "word": "BUMBLE"}, "46": {"clue": "Machine part", "word": "STATOR"}, "49": {"clue": "\"___ Town\"", "word": "OUR"}, "50": {"clue": "Rest of T. R.'s advice", "word": "CARRYABIGSTICK"}, "56": {"clue": "African tree", "word": "AKEE"}, "57": {"clue": "The sky, at times", "word": "LIMIT"}, "58": {"clue": "Hot-weather word", "word": "PHEW"}, "60": {"clue": "Horne", "word": "LENA"}, "61": {"clue": "French student", "word": "ELEVE"}, "62": {"clue": "Hebrides island", "word": "IONA"}, "63": {"clue": "Hindu land grant", "word": "ENAM"}, "64": {"clue": "Hinder", "word": "DETER"}, "65": {"clue": "Boodle", "word": "LOOT"}}, "down": {"1": {"clue": "Wood sorrel", "word": "OCA"}, "2": {"clue": "Lightning and fishing", "word": "RODS"}, "3": {"clue": "Not care ___", "word": "ARAP"}, "4": {"clue": "Dub", "word": "NAME"}, "5": {"clue": "German bombers", "word": "STUKAS"}, "6": {"clue": "Edith Cavell, for one", "word": "NURSE"}, "7": {"clue": "Something, in Spain", "word": "ALGO"}, "8": {"clue": "Bass or treble", "word": "CLEF"}, "9": {"clue": "Old World falcons", "word": "KESTRELS"}, "10": {"clue": "Execute a quiet ploy", "word": "PLAYPOSSUM"}, "11": {"clue": "Splendid", "word": "REGAL"}, "12": {"clue": "Foolish", "word": "INANE"}, "13": {"clue": "Antiquated", "word": "MOLDY"}, "21": {"clue": "Verily", "word": "AMEN"}, "22": {"clue": "Cover", "word": "LID"}, "25": {"clue": "Defect", "word": "FLAW"}, "26": {"clue": "Actress Lee", "word": "LILA"}, "27": {"clue": "Asian boundary river", "word": "AMUR"}, "28": {"clue": "Prevailing trend", "word": "MAINSTREAM"}, "29": {"clue": "Proofreading mark", "word": "CARET"}, "30": {"clue": "Pro ___", "word": "RATA"}, "32": {"clue": "Cotton pod", "word": "BOLL"}, "34": {"clue": "Metrical foot", "word": "IAMB"}, "35": {"clue": "Box or bag", "word": "MAIL"}, "36": {"clue": "English composer", "word": "ARNE"}, "38": {"clue": "Coiled", "word": "SPIRALED"}, "42": {"clue": "Brusque", "word": "CURT"}, "44": {"clue": "Trinket", "word": "TOY"}, "45": {"clue": "___ Brown", "word": "BUSTER"}, "46": {"clue": "Flake", "word": "SCALE"}, "47": {"clue": "Spoken for", "word": "TAKEN"}, "48": {"clue": "Ring", "word": "ARENA"}, "49": {"clue": "Pointed arch", "word": "OGIVE"}, "51": {"clue": "Peevishness", "word": "BILE"}, "52": {"clue": "\"___ a man with ... \"", "word": "IMET"}, "53": {"clue": "Brown-dye tree", "word": "IPIL"}, "54": {"clue": "Half a child's train", "word": "CHOO"}, "55": {"clue": "Gambling game", "word": "KENO"}, "59": {"clue": "Buddhist temple", "word": "WAT"}}}, "metadata": {"author": "Sara V. Tuckerman", "editor": "Will Weng", "rows": 15, "columns": 15, "date": {"month": 6, "day": 4, "year": 1975}}}