{"puzzle": "ANIMALFARM BAKU\nBONGJOONHO ARES\nIVEMOVEDON LOAM\nTAC BESO  ILANA\n  SEWS RUNNERUP\nTITLE ARNETT   \nATALL SARAH BUS\nRESELLS ELEMENT\nAMY DAUBS HORDE\n   FORMAT ELIOT\nDEBUNKED BIEN  \nELATE  IDIG GPA\nGENZ LEDERHOSEN\nACTE SWEETTREAT\nSTUD DEATHSTARE\n", "key": {"across": {"1": {"clue": "Veiled satire on Joseph Stalin", "word": "ANIMALFARM"}, "11": {"clue": "Capital of Azerbaijan", "word": "BAKU"}, "15": {"clue": "First Korean to win the Best Director Oscar", "word": "BONGJOONHO"}, "16": {"clue": "Father of Eros", "word": "ARES"}, "17": {"clue": "\"We are not getting back together\"", "word": "IVEMOVEDON"}, "18": {"clue": "Compost ingredient", "word": "LOAM"}, "19": {"clue": "Toe preceder", "word": "TAC"}, "20": {"clue": "Show of amor", "word": "BESO"}, "21": {"clue": "Glazer of \"Broad City\"", "word": "ILANA"}, "22": {"clue": "Puts in stitches", "word": "SEWS"}, "24": {"clue": "One who is so close (and yet so far)", "word": "RUNNERUP"}, "27": {"clue": "Part of a promotion negotiation", "word": "TITLE"}, "29": {"clue": "Will who voices BoJack Horseman on \"BoJack Horseman\"", "word": "ARNETT"}, "30": {"clue": "Even a smidgen", "word": "ATALL"}, "31": {"clue": "Old Testament figure who has a child while in her early 90s", "word": "SARAH"}, "32": {"clue": "Long way around town?", "word": "BUS"}, "35": {"clue": "Lists on eBay, say", "word": "RESELLS"}, "37": {"clue": "He or I, but not you?", "word": "ELEMENT"}, "39": {"clue": "Senator Klobuchar", "word": "AMY"}, "40": {"clue": "Smears", "word": "DAUBS"}, "42": {"clue": "Group of zombies", "word": "HORDE"}, "43": {"clue": "Style", "word": "FORMAT"}, "44": {"clue": "Poet who said \"If you aren't in over your head, how do you know how tall you are?\"", "word": "ELIOT"}, "45": {"clue": "Like the \"fact\" that humans use only 10% of their brains", "word": "DEBUNKED"}, "48": {"clue": "Adverb in both French and Spanish", "word": "BIEN"}, "49": {"clue": "Thrill", "word": "ELATE"}, "50": {"clue": "\"Gotcha!,\" once", "word": "IDIG"}, "52": {"clue": "Fig. that always includes a decimal", "word": "GPA"}, "55": {"clue": "Demographic of many TikTok users", "word": "GENZ"}, "56": {"clue": "Oktoberfest garb", "word": "LEDERHOSEN"}, "59": {"clue": "Entr'___", "word": "ACTE"}, "60": {"clue": "Rhyming term for a dessert", "word": "SWEETTREAT"}, "61": {"clue": "What might be on the tip of your tongue?", "word": "STUD"}, "62": {"clue": "Killer look", "word": "DEATHSTARE"}}, "down": {"1": {"clue": "Slightly", "word": "ABIT"}, "2": {"clue": "Observation from an observatory", "word": "NOVA"}, "3": {"clue": "Super-happy", "word": "INECSTASY"}, "4": {"clue": "Grand opening for a casino?", "word": "MGM"}, "5": {"clue": "A+ work", "word": "AJOBWELLDONE"}, "6": {"clue": "Start of a three-word alliterative name of a Shakespeare play", "word": "LOVES"}, "7": {"clue": "Rivals", "word": "FOES"}, "8": {"clue": "Where Catalan is the official language", "word": "ANDORRA"}, "9": {"clue": "Letter seen in a Christogram", "word": "RHO"}, "10": {"clue": "Many a fed. holiday", "word": "MON"}, "11": {"clue": "It may keep you on your toes", "word": "BALLET"}, "12": {"clue": "Like a cheering crowd", "word": "AROAR"}, "13": {"clue": "Actor Reeves", "word": "KEANU"}, "14": {"clue": "Hanging on a classroom wall, maybe", "word": "USMAP"}, "21": {"clue": "Tony-winning musical written by Lin-Manuel Miranda during his second year of college", "word": "INTHEHEIGHTS"}, "23": {"clue": "___ Woods, lead character in \"Legally Blonde\"", "word": "ELLE"}, "25": {"clue": "Turbulence", "word": "UNREST"}, "26": {"clue": "Cassady who inspired Kerouac", "word": "NEAL"}, "27": {"clue": "Figure skater Lipinski", "word": "TARA"}, "28": {"clue": "Romantic couple", "word": "ITEM"}, "29": {"clue": "Take on", "word": "ASSUME"}, "32": {"clue": "What Bristol Bay is an arm of", "word": "BERINGSEA"}, "33": {"clue": "Ctrl+Z", "word": "UNDO"}, "34": {"clue": "Proofer's 33-Down", "word": "STET"}, "36": {"clue": "Joy ride, for example", "word": "LARK"}, "38": {"clue": "Mexican sauce made from chili peppers and chocolate", "word": "MOLE"}, "41": {"clue": "\"I'd think twice about that\"", "word": "BADIDEA"}, "43": {"clue": "Messed (with)", "word": "FUTZED"}, "45": {"clue": "Painter and devotee of 11-Down", "word": "DEGAS"}, "46": {"clue": "About to be in office", "word": "ELECT"}, "47": {"clue": "African language family", "word": "BANTU"}, "48": {"clue": "Special delivery", "word": "BIRTH"}, "51": {"clue": "Bug spray ingredient", "word": "DEET"}, "53": {"clue": "Lute shape", "word": "PEAR"}, "54": {"clue": "Kick in", "word": "ANTE"}, "56": {"clue": "Colorless, odorless drug", "word": "LSD"}, "57": {"clue": "First mammal to be cloned", "word": "EWE"}, "58": {"clue": "Food scrap", "word": "ORT"}}}, "metadata": {"author": "Kyra Wilson and Sophia Maymudes", "editor": "Will Shortz", "rows": 15, "columns": 15, "date": {"month": 4, "day": 2, "year": 2021}}}