{"puzzle": "BASH SPICA FRAT\nARTE OOTID RULE\nINON RESTRAINED\nTEAPARTY ELATES\n   EXES ONER   \nPARCEL SPARSELY\nLEEKS SHALT POE\nARCS REELS CODA\nIIO FEEDS CADET\nDENTISTS DURESS\n   ASTO BART   \nALASKA TAILORED\nMATTERHORN OILY\nALOE TAROT NOSE\nHAND STONY STAR\n", "key": {"across": {"1": {"clue": "Lively shindig", "word": "BASH"}, "5": {"clue": "Star in Virgo", "word": "SPICA"}, "10": {"clue": "College org.", "word": "FRAT"}, "14": {"clue": "Comedian Johnson", "word": "ARTE"}, "15": {"clue": "Egg cell", "word": "OOTID"}, "16": {"clue": "___ of thumb", "word": "RULE"}, "17": {"clue": "Sharing the plot", "word": "INON"}, "18": {"clue": "Showing discipline", "word": "RESTRAINED"}, "20": {"clue": "Event for Alice", "word": "TEAPARTY"}, "22": {"clue": "Puts into ecstasy", "word": "ELATES"}, "23": {"clue": "Tic-tac-toe side", "word": "EXES"}, "24": {"clue": "Special person", "word": "ONER"}, "25": {"clue": "C.O.D. item", "word": "PARCEL"}, "28": {"clue": "How Nevada is populated", "word": "SPARSELY"}, "32": {"clue": "Soup vegetables", "word": "LEEKS"}, "33": {"clue": "Biblical verb", "word": "SHALT"}, "34": {"clue": "Raven man", "word": "POE"}, "35": {"clue": "Windshield-wiper sweeps", "word": "ARCS"}, "36": {"clue": "Rods' partners", "word": "REELS"}, "37": {"clue": "Musical passage", "word": "CODA"}, "38": {"clue": "Second-century date", "word": "IIO"}, "39": {"clue": "Nourishes", "word": "FEEDS"}, "40": {"clue": "West Point figure", "word": "CADET"}, "41": {"clue": "Cap and crown men", "word": "DENTISTS"}, "43": {"clue": "Constraint", "word": "DURESS"}, "44": {"clue": "In re", "word": "ASTO"}, "45": {"clue": "San Francisco's metro", "word": "BART"}, "46": {"clue": "Seward's buy", "word": "ALASKA"}, "49": {"clue": "Made-to-order", "word": "TAILORED"}, "53": {"clue": "Zermatt sight", "word": "MATTERHORN"}, "55": {"clue": "Unctuous", "word": "OILY"}, "56": {"clue": "Bitter drug", "word": "ALOE"}, "57": {"clue": "Fortune-telling card", "word": "TAROT"}, "58": {"clue": "___ for news", "word": "NOSE"}, "59": {"clue": "Palm site", "word": "HAND"}, "60": {"clue": "Sphinx-like", "word": "STONY"}, "61": {"clue": "Top-billed one", "word": "STAR"}}, "down": {"1": {"clue": "Lure", "word": "BAIT"}, "2": {"clue": "English composer", "word": "ARNE"}, "3": {"clue": "Portico", "word": "STOA"}, "4": {"clue": "Gives no peace", "word": "HENPECKS"}, "5": {"clue": "Horse color", "word": "SORREL"}, "6": {"clue": "Certain writers", "word": "POETS"}, "7": {"clue": "___-bitsy", "word": "ITSY"}, "8": {"clue": "Townsman", "word": "CIT"}, "9": {"clue": "Certain glands", "word": "ADRENALS"}, "10": {"clue": "Tuck et al.", "word": "FRIARS"}, "11": {"clue": "Litter's also-ran", "word": "RUNT"}, "12": {"clue": "Sheltered", "word": "ALEE"}, "13": {"clue": "Williams and Husing", "word": "TEDS"}, "19": {"clue": "On one's toes", "word": "ALERT"}, "21": {"clue": "Chops", "word": "AXES"}, "24": {"clue": "October stones", "word": "OPALS"}, "25": {"clue": "Scottish wear", "word": "PLAID"}, "26": {"clue": "Eagle's nest", "word": "AERIE"}, "27": {"clue": "Military search, for short", "word": "RECON"}, "28": {"clue": "Water and wood", "word": "SHEDS"}, "29": {"clue": "Lyric poem", "word": "EPODE"}, "30": {"clue": "Rich veins", "word": "LODES"}, "31": {"clue": "\"Byzantium\" poet", "word": "YEATS"}, "33": {"clue": "Take care of", "word": "SEETO"}, "36": {"clue": "Makes a fresh beginning", "word": "RESTARTS"}, "37": {"clue": "\"Peanuts\" and \"Miss Peach\"", "word": "CARTOONS"}, "39": {"clue": "Minnie Maddern of stage", "word": "FISKE"}, "40": {"clue": "Play an ice game", "word": "CURL"}, "42": {"clue": "Sampled", "word": "TASTED"}, "43": {"clue": "Overnice", "word": "DAINTY"}, "45": {"clue": "Robber ___", "word": "BARON"}, "46": {"clue": "Asian nurse", "word": "AMAH"}, "47": {"clue": "Tra-___", "word": "LALA"}, "48": {"clue": "Egyptian god", "word": "ATON"}, "49": {"clue": "Spanish bull", "word": "TORO"}, "50": {"clue": "Disturbance", "word": "RIOT"}, "51": {"clue": "Miss Lanchester", "word": "ELSA"}, "52": {"clue": "Color worker", "word": "DYER"}, "54": {"clue": "Old or top", "word": "HAT"}}}, "metadata": {"author": "Mike Moore", "editor": "Will Weng", "rows": 15, "columns": 15, "date": {"month": 6, "day": 4, "year": 1974}}}