{"puzzle": "FORMAL DUMB CHI\nAVIATE OVAL HON\nKILIMANJARO OWL\nEDEN ROO  NOISE\n   DENISDIDEROT\nMERITS  EMER   \nELISA CLIP  BCE\nSUCHSWEETSORROW\nALE  OLAY LEAVE\n   SPEE  SETTER\nCENSUSBUREAU   \nALIEN  SUR RASH\nBIN JAMESMONROE\nLOT AGAR ONEILL\nETH BEDS NODDED\n", "key": {"across": {"1": {"clue": "White-tie event", "word": "FORMAL"}, "7": {"clue": "Half-baked", "word": "DUMB"}, "11": {"clue": "Home of the Bulls, informally", "word": "CHI"}, "14": {"clue": "Lead zeppelins?", "word": "AVIATE"}, "15": {"clue": "Track shape", "word": "OVAL"}, "16": {"clue": "Darling", "word": "HON"}, "17": {"clue": "Africa's highest peak", "word": "KILIMANJARO"}, "19": {"clue": "One who gives a hoot?", "word": "OWL"}, "20": {"clue": "Starting point?", "word": "EDEN"}, "21": {"clue": "Son of Kanga", "word": "ROO"}, "22": {"clue": "Reason to wear earplugs", "word": "NOISE"}, "24": {"clue": "Noted French encyclopedist", "word": "DENISDIDEROT"}, "28": {"clue": "Scouts earn them", "word": "MERITS"}, "31": {"clue": "Like a 911 call Abbr.", "word": "EMER"}, "32": {"clue": "Girl in a \"Paint Your Wagon\" song", "word": "ELISA"}, "33": {"clue": "Part of a televised movie review", "word": "CLIP"}, "35": {"clue": "Letters after old dates", "word": "BCE"}, "38": {"clue": "Parting, to Juliet", "word": "SUCHSWEETSORROW"}, "42": {"clue": "Hoppy brew", "word": "ALE"}, "43": {"clue": "Maker of the face cream Regenerist", "word": "OLAY"}, "44": {"clue": "\"Begone!\"", "word": "LEAVE"}, "45": {"clue": "German W.W. I admiral", "word": "SPEE"}, "47": {"clue": "Hunting dog", "word": "SETTER"}, "48": {"clue": "Group you can rely on when it counts", "word": "CENSUSBUREAU"}, "53": {"clue": "Unearthly", "word": "ALIEN"}, "54": {"clue": "California's Big ___", "word": "SUR"}, "55": {"clue": "Not thought through", "word": "RASH"}, "59": {"clue": "Recyclables container", "word": "BIN"}, "60": {"clue": "President who lived at Oak Hill", "word": "JAMESMONROE"}, "64": {"clue": "Polish airline", "word": "LOT"}, "65": {"clue": "Food thickener", "word": "AGAR"}, "66": {"clue": "Playwright Eugene", "word": "ONEILL"}, "67": {"clue": "Ordinal suffix", "word": "ETH"}, "68": {"clue": "Hospital capacity", "word": "BEDS"}, "69": {"clue": "Silently assented", "word": "NODDED"}}, "down": {"1": {"clue": "Like knockoff goods", "word": "FAKE"}, "2": {"clue": "Golden Age poet", "word": "OVID"}, "3": {"clue": "Tick off", "word": "RILE"}, "4": {"clue": "Entree", "word": "MAINDISH"}, "5": {"clue": "Cash cache", "word": "ATM"}, "6": {"clue": "Gets the hang of", "word": "LEARNS"}, "7": {"clue": "Karate schools", "word": "DOJOS"}, "8": {"clue": "Cavaliers of the N.C.A.A.", "word": "UVA"}, "9": {"clue": "Vandalize, e.g.", "word": "MAR"}, "10": {"clue": "Mae West or Cheryl Tiegs", "word": "BLONDE"}, "11": {"clue": "Preaching to the ___", "word": "CHOIR"}, "12": {"clue": "\"In what way?\"", "word": "HOWSO"}, "13": {"clue": "Puget Sound, e.g.", "word": "INLET"}, "18": {"clue": "\"___ didn't!\"", "word": "NOI"}, "23": {"clue": "Anthem contraction", "word": "OER"}, "25": {"clue": "O'Hare info, for short", "word": "ETAS"}, "26": {"clue": "Saturn or Mercury", "word": "DEITY"}, "27": {"clue": "Babysitters' challenges", "word": "IMPS"}, "28": {"clue": "Arizona's third-largest city", "word": "MESA"}, "29": {"clue": "Hebrew month", "word": "ELUL"}, "30": {"clue": "It might be wild or dirty", "word": "RICE"}, "33": {"clue": "A-lister", "word": "CELEB"}, "34": {"clue": "Open field", "word": "LEA"}, "35": {"clue": "Babysitter's challenge", "word": "BRAT"}, "36": {"clue": "Place to moor a boat", "word": "COVE"}, "37": {"clue": "Fancy pitcher", "word": "EWER"}, "39": {"clue": "Trials and tribulations", "word": "WOES"}, "40": {"clue": "Olive genus", "word": "OLEA"}, "41": {"clue": "Like a bad check", "word": "RETURNED"}, "45": {"clue": "Opposite of NNW", "word": "SSE"}, "46": {"clue": "Indian state whose name means \"five rivers\"", "word": "PUNJAB"}, "47": {"clue": "Church address", "word": "SERMON"}, "48": {"clue": "Not broadcast", "word": "CABLE"}, "49": {"clue": "Poet who wrote \"This is the way the world ends / Not with a bang but a whimper\"", "word": "ELIOT"}, "50": {"clue": "Inning for closers", "word": "NINTH"}, "51": {"clue": "Consumers", "word": "USERS"}, "52": {"clue": "St. Petersburg's home Abbr.", "word": "RUS"}, "56": {"clue": "Like Death Valley", "word": "ARID"}, "57": {"clue": "One and only", "word": "SOLE"}, "58": {"clue": "Detained", "word": "HELD"}, "61": {"clue": "Digital ___", "word": "AGE"}, "62": {"clue": "Magazine written by \"the usual gang of idiots\"", "word": "MAD"}, "63": {"clue": "John Lennon's middle name", "word": "ONO"}}}, "metadata": {"author": "James Tuttle", "editor": "Will Shortz", "rows": 15, "columns": 15, "date": {"month": 1, "day": 27, "year": 2015}}}