{"puzzle": "RIFE PRATT BRAN\nENOS RICHE IONA\nERRS OCEANSTATE\nVOTESFORWOMEN  \nEARNS   SRA    \nDDE TYKE  RACER\n  SUSANBANTHONY\nMASC DOONE MUSE\nAMELIABLOOMER  \nHASAT  ANNA TNT\n    ATF   USHER\n  JULIAWARDHOWE\nPHONOGRAPH RUMP\nHELD RADIO ESAI\nINTO EDENS WEND\n", "key": {"across": {"1": {"clue": "Prevalent", "word": "RIFE"}, "5": {"clue": "___ & Whitney (aircraft engine manufacturer)", "word": "PRATT"}, "10": {"clue": "Flake material", "word": "BRAN"}, "14": {"clue": "Book of the Book of Mormon", "word": "ENOS"}, "15": {"clue": "Nouveau ___", "word": "RICHE"}, "16": {"clue": "College in New Rochelle, N.Y.", "word": "IONA"}, "17": {"clue": "Barks up the wrong tree", "word": "ERRS"}, "18": {"clue": "Rhode Island, with \"the\"", "word": "OCEANSTATE"}, "20": {"clue": "See 34-, 42- and 55-Across", "word": "VOTESFORWOMEN"}, "22": {"clue": "Rakes in", "word": "EARNS"}, "23": {"clue": "Mme., across the Pyrenees", "word": "SRA"}, "24": {"clue": "Subj. of a 1984 Stephen Ambrose political biography", "word": "DDE"}, "25": {"clue": "Daycare charge", "word": "TYKE"}, "29": {"clue": "Speed demon", "word": "RACER"}, "34": {"clue": "19th-century writer/lecturer who advocated 20-Across", "word": "SUSANBANTHONY"}, "38": {"clue": "Like \"der,\" in Ger.", "word": "MASC"}, "40": {"clue": "\"Lorna ___\"", "word": "DOONE"}, "41": {"clue": "Inspirer", "word": "MUSE"}, "42": {"clue": "19th-century dress reformer who advocated 20-Across", "word": "AMELIABLOOMER"}, "45": {"clue": "Attacks", "word": "HASAT"}, "46": {"clue": "Trollope's \"Lady ___\"", "word": "ANNA"}, "47": {"clue": "It may give you a charge", "word": "TNT"}, "50": {"clue": "Fed. bureau with agents", "word": "ATF"}, "53": {"clue": "Walk down the aisle?", "word": "USHER"}, "55": {"clue": "19th-century author/hymnist who advocated 20-Across", "word": "JULIAWARDHOWE"}, "60": {"clue": "Needle holder", "word": "PHONOGRAPH"}, "62": {"clue": "Rear end", "word": "RUMP"}, "63": {"clue": "Retained", "word": "HELD"}, "64": {"clue": "It has bands with music", "word": "RADIO"}, "65": {"clue": "Morales of \"N.Y.P.D. Blue\"", "word": "ESAI"}, "66": {"clue": "Division preposition", "word": "INTO"}, "67": {"clue": "Idyllic spots", "word": "EDENS"}, "68": {"clue": "Proceed", "word": "WEND"}}, "down": {"1": {"clue": "Passed through, as a rope", "word": "REEVED"}, "2": {"clue": "Encroachment", "word": "INROAD"}, "3": {"clue": "Strongholds", "word": "FORTRESSES"}, "4": {"clue": "German steel city", "word": "ESSEN"}, "5": {"clue": "Univ. V.I.P.", "word": "PROF"}, "6": {"clue": "Wealthy, in Ju\u00e1rez", "word": "RICO"}, "7": {"clue": "Whiz of a tennis server", "word": "ACER"}, "8": {"clue": "D\u00e9tentes", "word": "THAWS"}, "9": {"clue": "___ sax", "word": "TENOR"}, "10": {"clue": "Snack", "word": "BITE"}, "11": {"clue": "Flecked horse", "word": "ROAN"}, "12": {"clue": "Six-footer", "word": "ANT"}, "13": {"clue": "Dundee denial", "word": "NAE"}, "19": {"clue": "Sassy", "word": "SMART"}, "21": {"clue": "Grounded jets", "word": "SSTS"}, "26": {"clue": "When said three times, \"et cetera\"", "word": "YADA"}, "27": {"clue": "Tree or door feature", "word": "KNOB"}, "28": {"clue": "Dreaded virus", "word": "EBOLA"}, "30": {"clue": "\"Alas!\"", "word": "AHME"}, "31": {"clue": "Place to get hitched, perhaps", "word": "COURTHOUSE"}, "32": {"clue": "Dash lengths", "word": "ENS"}, "33": {"clue": "Certain whiskey", "word": "RYE"}, "35": {"clue": "Bruins home, for short", "word": "UCLA"}, "36": {"clue": "Like many a quip Abbr.", "word": "ANON"}, "37": {"clue": "\"Open all night\" sign, maybe", "word": "NEON"}, "38": {"clue": "___-jongg", "word": "MAH"}, "39": {"clue": "Grp. with a famous journal", "word": "AMA"}, "43": {"clue": "Author Calvino", "word": "ITALO"}, "44": {"clue": "Antarctica's Queen ___ Mountains", "word": "MAUD"}, "48": {"clue": "\"Seinfeld\" character", "word": "NEWMAN"}, "49": {"clue": "Fearful", "word": "TREPID"}, "51": {"clue": "Feline in un jardin zoologique", "word": "TIGRE"}, "52": {"clue": "Measure of capacitance", "word": "FARAD"}, "54": {"clue": "Nag", "word": "SHREW"}, "55": {"clue": "Elbow hard", "word": "JOLT"}, "56": {"clue": "Word processor command", "word": "UNDO"}, "57": {"clue": "Baseballer Boggs", "word": "WADE"}, "58": {"clue": "Neat as ___", "word": "APIN"}, "59": {"clue": "Fraternity letters", "word": "RHOS"}, "60": {"clue": "___ Beta Kappa", "word": "PHI"}, "61": {"clue": "Setter", "word": "HEN"}}}, "metadata": {"author": "Stella Daily and Bruce Venzke", "editor": "Will Shortz", "rows": 15, "columns": 15, "date": {"month": 8, "day": 26, "year": 2004}}}