{"puzzle": "AMUR SMELT SCAR\nNOTE TABOO HOME\nSTAMPALBUM ALIF\nATHEART DOGSLED\n   DIVA  ROTE  \nREPINE BARNACLE\nACHES MAGOG TEA\nVOID BELOW TIAS\nELL HELEN AROSE\nSEAPORTS ALINED\n  TERR  ATEE   \nTHEDAYS CHASTEN\nHOLD POSTOFFICE\nANIL IDIOM ODOR\nNICE EAGRE RENO\n", "key": {"across": {"1": {"clue": "River of Asia.", "word": "AMUR"}, "5": {"clue": "Food fish.", "word": "SMELT"}, "10": {"clue": "Mark.", "word": "SCAR"}, "14": {"clue": "Eminence.", "word": "NOTE"}, "15": {"clue": "Proscribed.", "word": "TABOO"}, "16": {"clue": "Name in the headlines.", "word": "HOME"}, "17": {"clue": "Container for certain adhesives.", "word": "STAMPALBUM"}, "19": {"clue": "Arabic letter.", "word": "ALIF"}, "20": {"clue": "Basically.", "word": "ATHEART"}, "21": {"clue": "Arctic item.", "word": "DOGSLED"}, "23": {"clue": "Singer.", "word": "DIVA"}, "24": {"clue": "Sound of surf.", "word": "ROTE"}, "25": {"clue": "Complain.", "word": "REPINE"}, "28": {"clue": "Sea animal.", "word": "BARNACLE"}, "32": {"clue": "Yearnings.", "word": "ACHES"}, "33": {"clue": "Famous London statue.", "word": "MAGOG"}, "34": {"clue": "Reception.", "word": "TEA"}, "35": {"clue": "Ineffective.", "word": "VOID"}, "36": {"clue": "On earth.", "word": "BELOW"}, "37": {"clue": "Spanish aunts.", "word": "TIAS"}, "38": {"clue": "House part.", "word": "ELL"}, "39": {"clue": "Figure in Greek legend.", "word": "HELEN"}, "40": {"clue": "Answered the alarm.", "word": "AROSE"}, "41": {"clue": "Where the United States stops.", "word": "SEAPORTS"}, "43": {"clue": "Straightened.", "word": "ALINED"}, "44": {"clue": "Region Abbr.", "word": "TERR"}, "45": {"clue": "To ___ (precisely).", "word": "ATEE"}, "46": {"clue": "\"Those were ___.\"", "word": "THEDAYS"}, "49": {"clue": "Subdue.", "word": "CHASTEN"}, "53": {"clue": "Occupy.", "word": "HOLD"}, "54": {"clue": "Children's game.", "word": "POSTOFFICE"}, "56": {"clue": "Indigo.", "word": "ANIL"}, "57": {"clue": "Manner of speaking.", "word": "IDIOM"}, "58": {"clue": "Scent.", "word": "ODOR"}, "59": {"clue": "Fastidious.", "word": "NICE"}, "60": {"clue": "Tidal bore.", "word": "EAGRE"}, "61": {"clue": "City on the Truckee.", "word": "RENO"}}, "down": {"1": {"clue": "Handle Lat.", "word": "ANSA"}, "2": {"clue": "American feminist.", "word": "MOTT"}, "3": {"clue": "Where Ogden is.", "word": "UTAH"}, "4": {"clue": "Corrected.", "word": "REMEDIED"}, "5": {"clue": "___ for (be in great need of).", "word": "STARVE"}, "6": {"clue": "Gozo's neighbor.", "word": "MALTA"}, "7": {"clue": "Recede.", "word": "EBB"}, "8": {"clue": "Clamorous.", "word": "LOUD"}, "9": {"clue": "Time for doing things.", "word": "TOMORROW"}, "10": {"clue": "Cascades peak.", "word": "SHASTA"}, "11": {"clue": "Contents of 17 Across.", "word": "COLLECTION"}, "12": {"clue": "French friend.", "word": "AMIE"}, "13": {"clue": "Assigned (to) Abbr.", "word": "REFD"}, "18": {"clue": "Great care.", "word": "PAINS"}, "22": {"clue": "Dinner bell.", "word": "GONG"}, "25": {"clue": "Certain reviews.", "word": "RAVES"}, "26": {"clue": "___ des Beaux-Arts.", "word": "ECOLE"}, "27": {"clue": "Of the contents of 17 Across.", "word": "PHILATELIC"}, "28": {"clue": "Bundles.", "word": "BALES"}, "29": {"clue": "Dramatic conflict, from the Greek.", "word": "AGON"}, "30": {"clue": "Contract.", "word": "LEASE"}, "31": {"clue": "Let up.", "word": "EASED"}, "33": {"clue": "Disappear.", "word": "MELT"}, "36": {"clue": "Dessert.", "word": "BERRYPIE"}, "37": {"clue": "Attempts to get.", "word": "TRIESFOR"}, "39": {"clue": "Latin hour.", "word": "HORA"}, "40": {"clue": "\"And we all do fade as ___.\"", "word": "ALEAF"}, "42": {"clue": "Sell.", "word": "PEDDLE"}, "43": {"clue": "Type of party.", "word": "ATHOME"}, "45": {"clue": "Member of Equity.", "word": "ACTOR"}, "46": {"clue": "Particle of comparison.", "word": "THAN"}, "47": {"clue": "\"___ soit ... \"", "word": "HONI"}, "48": {"clue": "Mixer.", "word": "SODA"}, "50": {"clue": "Time's partner.", "word": "TIDE"}, "51": {"clue": "Course of study Abbr.", "word": "ECON"}, "52": {"clue": "Blackness It.", "word": "NERO"}, "55": {"clue": "Written name Abbr.", "word": "SIG"}}}, "metadata": {"author": "A. H. Drummond, Jr.", "editor": "Margaret Farrar", "rows": 15, "columns": 15, "date": {"month": 11, "day": 11, "year": 1963}}}